{
  "turret": {
    "name": "concentration",
    "class": "ContinuousTurret",
    "requirements": {
      "category": "turret",
      "items": {
        "carbide": 150,
        "setonAlloy": 80,
        "seniorProcessor": 75
      }
    },
    "overheatSystem": {
      "overheatTime": 900,
      "overheatCoolAmount": 3,
      "slowDownReloadTime": 150,
      "chargeTime": 300,
      "maxHeatEffectChance": 0.3,
      "heatEffect": "reactorsmoke"
    },
    "stats": {
      "shootWarmupSpeed": 0.04,
      "shootCone": 360,
      "aimChangeSpeed": 1.75,
      "rotateSpeed": 1.45,
      "canOverdrive": false,
      "shootY": 16,
      "minWarmup": 0.8,
      "warmupMaintainTime": 45,
      "outlineColor": "darkOutline",
      "size": 5,
      "range": 600,
      "scaledHealth": 300,
      "armor": 10,
      "unitSort": "slowest",
      "consumePower": 16,
      "consumeLiquidPerSecond": {
        "water": 0.2
      }
    },
    "drawer": {
      "parts": [
        {
          "name": "-charger",
          "mirror": true,
          "under": true,
          "moveRot": 10,
          "moveX": 4.677,
          "moveY": 6.8
        },
        {
          "name": "-side",
          "mirror": true,
          "under": true,
          "moveRot": 10,
          "moveX": 2.75,
          "moveY": 2
        },
        {
          "name": "-barrel",
          "moveY": -7.5,
          "progress": "Warmup"
        }
      ]
    },
    "sound": {
      "shootSound": "none",
      "loopSound": "largeBeam",
      "loopSoundVolume": 1.0
    },
    "bullet": {
      "class": "UpgradePointLaserBulletType",
      "damage": 200,
      "shieldDamageMultiplier": 2,
      "buildingDamageMultiplier": 0.5,
      "damageInterval": 6,
      "statusEffect": "wet",
      "statusDuration": 60,
      "sprite": "laser-white",
      "trailLength": 8,
      "oscScl": 2,
      "oscMag": 0.3,
      "range": 600,
      "chargeReload": 300,
      "lerpReload": 10,
      "maxDamageMultiplier": 5,
      "bundleName": "coucou"
    }
  }
}
